{
  "id": "Canadian_Grey",
  "order": 2,
  "title": "Canadian Grey",
  "type": "spc",
  "image": "../../assets/imgs/pisos/canadian_grey/canadian_grey.png",
  "bannerImgs": [
    "../../assets/imgs/pisos/canadian_grey/canadian_greyPortada.jpg",
    "../../assets/imgs/pisos/canadian_grey/canadian_grey.png"
  ],
  "similarProductIDs": ["carbon", "coco_oak", "massy_oak", "white_oak"],
  "dimensions" : "7.2” x 48” (183 mm x 1220mm)",
  "totalThickness": "5.5 mm (Con espuma IXPE de 1.5 mm)",
  "wearLayer": "0.5 mm (20 mils)"
}
